faunanet_record/__init__.py
faunanet_record/audio_recording.py
faunanet_record/cli.py
faunanet_record/default.yml
faunanet_record/install.yml
faunanet_record/runner.py
faunanet_record/set_up.py
faunanet_record/utils.py
faunanet_record/docker/faunanet_record.dockerfile
faunanet_record/docker/iotest.py
faunanet_record/docker/test.dockerfile
faunanet_record-0.0.14.dist-info/LICENSE
faunanet_record-0.0.14.dist-info/METADATA
faunanet_record-0.0.14.dist-info/WHEEL
faunanet_record-0.0.14.dist-info/entry_points.txt
faunanet_record-0.0.14.dist-info/top_level.txt
faunanet_record-0.0.14.dist-info/RECORD
