Metadata-Version: 2.1
Name: faunanet-record
Version: 0.0.14
Summary: Audio Recording Facilities for the isparrow package
Author-email: Harald Mack <harald.mack@iwr.uni-heidelberg.de>, Inga Ulusoy <inga.ulusoy@uni-heidelberg.de>
License: Apache License
Project-URL: Repository, https://github.com/ssciwr/iSparrowRecord
Project-URL: Issues, https://github.com/ssciwr/iSparrowRecord/issues
Classifier: Programming Language :: Python :: 3
Classifier: Operating System :: POSIX :: Linux
Classifier: License :: OSI Approved :: Apache Software License
Classifier: Topic :: Multimedia :: Sound/Audio :: Capture/Recording
Classifier: Development Status :: 4 - Beta
Requires-Python: >=3.9
License-File: LICENSE
Requires-Dist: numpy
Requires-Dist: PyYAML
Requires-Dist: wave
Requires-Dist: pyaudio
Requires-Dist: platformdirs
Requires-Dist: click
Provides-Extra: dev
Requires-Dist: pytest ; extra == 'dev'
Requires-Dist: pytest-cov ; extra == 'dev'
Requires-Dist: coverage ; extra == 'dev'
Requires-Dist: pre-commit ; extra == 'dev'
Requires-Dist: librosa ; extra == 'dev'
Provides-Extra: doc
Requires-Dist: sphinx ; extra == 'doc'
Requires-Dist: myst-parser ; extra == 'doc'
Requires-Dist: sphinxcontrib-napoleon ; extra == 'doc'
Requires-Dist: sphinx-rtd-theme ; extra == 'doc'
